mooda/__init__.py
mooda/input/__init__.py
mooda/input/from_erddap.py
mooda/input/read_dat_td_pati.py
mooda/input/read_df.py
mooda/input/read_json.py
mooda/input/read_nc.py
mooda/input/read_pkl.py
mooda/util/__init__.py
mooda/util/concat.py
mooda/util/emso.py
mooda/util/es_create_indexes.py
mooda/util/md5.py
mooda/util/iplot/__init__.py
mooda/util/iplot/iplot_line.py
mooda/util/iplot/iplot_location.py
mooda/util/iplot/iplot_timeseries.py
mooda/util/md_widgets/__init__.py
mooda/util/md_widgets/widget_emso.py
mooda/util/md_widgets/widget_emso_qc.py
mooda/util/md_widgets/widget_qc.py
mooda/util/md_widgets/widget_save.py
mooda/waterframe/__init__.py
mooda/waterframe/analysis/__init__.py
mooda/waterframe/analysis/asal_temp2dens.py
mooda/waterframe/analysis/copy.py
mooda/waterframe/analysis/corr.py
mooda/waterframe/analysis/drop.py
mooda/waterframe/analysis/info_metadata.py
mooda/waterframe/analysis/info_vocabulary.py
mooda/waterframe/analysis/max.py
mooda/waterframe/analysis/max_diff.py
mooda/waterframe/analysis/min.py
mooda/waterframe/analysis/pres2depth.py
mooda/waterframe/analysis/psal2asal.py
mooda/waterframe/analysis/reduce_memory.py
mooda/waterframe/analysis/rename.py
mooda/waterframe/analysis/resample.py
mooda/waterframe/analysis/slice_time.py
mooda/waterframe/analysis/time_intervals.py
mooda/waterframe/analysis/use_only.py
mooda/waterframe/iplot/__init__.py
mooda/waterframe/iplot/_iplot_line.py
mooda/waterframe/iplot/iplot.py
mooda/waterframe/iplot/iplot_bar_polar.py
mooda/waterframe/iplot/iplot_box.py
mooda/waterframe/iplot/iplot_candlestick.py
mooda/waterframe/iplot/iplot_correlation_headmap.py
mooda/waterframe/iplot/iplot_data_intervals.py
mooda/waterframe/iplot/iplot_histogram.py
mooda/waterframe/iplot/iplot_line.py
mooda/waterframe/iplot/iplot_location.py
mooda/waterframe/iplot/iplot_scatter.py
mooda/waterframe/iplot/iplot_scatter_mapbox.py
mooda/waterframe/iplot/iplot_timeseries.py
mooda/waterframe/output/__init__.py
mooda-2.0.0.dist-info/LICENSE
mooda-2.0.0.dist-info/METADATA
mooda-2.0.0.dist-info/WHEEL
mooda-2.0.0.dist-info/top_level.txt
mooda-2.0.0.dist-info/RECORD
